nostocalean/__init__.py
nostocalean/flavor.py
nostocalean/functions.py
nostocalean/hf.py
nostocalean/nt.py
nostocalean/plotting.py
nostocalean/rpy2utils.py
nostocalean/sest.py
nostocalean/utility_functions.py
nostocalean/est/__init__.py
nostocalean/est/did.py
nostocalean/est/fixest.py
nostocalean-0.0.16.dist-info/LICENSE
nostocalean-0.0.16.dist-info/METADATA
nostocalean-0.0.16.dist-info/WHEEL
nostocalean-0.0.16.dist-info/top_level.txt
nostocalean-0.0.16.dist-info/RECORD
