Metadata-Version: 2.1
Name: nostocalean
Version: 0.0.16
Summary: Custom utility functions.
Home-page: https://github.com/suproteemsarkar/nostocalean
Author: Suproteem Sarkar
License: MIT
Requires-Python: >=3.5
License-File: LICENSE
